unifi/__init__.py
unifi/controller.py
unifi/exceptions.py
unifi_api-1.0.3.dist-info/LICENSE
unifi_api-1.0.3.dist-info/METADATA
unifi_api-1.0.3.dist-info/WHEEL
unifi_api-1.0.3.dist-info/top_level.txt
unifi_api-1.0.3.dist-info/RECORD
