Metadata-Version: 2.1
Name: unifi-api
Version: 1.0.3
Summary: API Ubiquity UniFi Controller
Home-page: https://github.com/fgbs/unifi
Author: Felipe Barros
Author-email: felipe.barros@gmail.com
License: UNKNOWN
Platform: UNKNOWN
Classifier: Intended Audience :: Developers
Classifier: License :: OSI Approved :: MIT License
Classifier: Topic :: Software Development :: Libraries
Classifier: Topic :: System :: Networking
Requires-Dist: requests
Requires-Dist: requests-toolbelt
